odoo/addons/stock_move_location_dest_constraint_base/README.rst
odoo/addons/stock_move_location_dest_constraint_base/__init__.py
odoo/addons/stock_move_location_dest_constraint_base/__manifest__.py
odoo/addons/stock_move_location_dest_constraint_base/data/stock_location.xml
odoo/addons/stock_move_location_dest_constraint_base/i18n/stock_move_location_dest_constraint_base.pot
odoo/addons/stock_move_location_dest_constraint_base/models/__init__.py
odoo/addons/stock_move_location_dest_constraint_base/models/product_strategy.py
odoo/addons/stock_move_location_dest_constraint_base/models/stock_location.py
odoo/addons/stock_move_location_dest_constraint_base/models/stock_move.py
odoo/addons/stock_move_location_dest_constraint_base/readme/CONFIGURE.rst
odoo/addons/stock_move_location_dest_constraint_base/readme/CONTRIBUTORS.rst
odoo/addons/stock_move_location_dest_constraint_base/readme/DESCRIPTION.rst
odoo/addons/stock_move_location_dest_constraint_base/readme/USAGE.rst
odoo/addons/stock_move_location_dest_constraint_base/static/description/icon.png
odoo/addons/stock_move_location_dest_constraint_base/static/description/index.html
odoo/addons/stock_move_location_dest_constraint_base/views/stock_location.xml
odoo12_addon_stock_move_location_dest_constraint_base-12.0.1.0.0.99.dev8.dist-info/METADATA
odoo12_addon_stock_move_location_dest_constraint_base-12.0.1.0.0.99.dev8.dist-info/WHEEL
odoo12_addon_stock_move_location_dest_constraint_base-12.0.1.0.0.99.dev8.dist-info/top_level.txt
odoo12_addon_stock_move_location_dest_constraint_base-12.0.1.0.0.99.dev8.dist-info/RECORD
