Metadata-Version: 2.1
Name: odoo12-addon-stock-move-location-dest-constraint-base
Version: 12.0.1.0.0.99.dev8
Summary: Base module to constrain dest location on stock move line
Home-page: https://github.com/OCA/stock-logistics-warehouse
Author: Camptocamp, Odoo Community Association (OCA)
Author-email: support@odoo-community.org
License: AGPL-3
Platform: UNKNOWN
Classifier: Programming Language :: Python
Classifier: Framework :: Odoo
Classifier: License :: OSI Approved :: GNU Affero General Public License v3
Classifier: Development Status :: 3 - Alpha
Requires-Python: >=3.5
Requires-Dist: odoo12-addon-stock-putaway-rule
Requires-Dist: odoo (<12.1dev,>=12.0a)
